{
  "clients": [
    {
      "first_name": "Jane",
      "last_name": "Doe",
      "organization": "ABC Corp",
      "email": "janedoe@freshbooks.com",
      "username": "janedoe",
      "password": "seCret!7",
      "contacts": {
        "contact": {
          "username": "alex",
          "first_name": "",
          "last_name": "",
          "email": "test@freshbooks.com",
          "phone1": "",
          "phone2": ""
        }
      },
      "work_phone": "(555) 123-4567",
      "home_phone": "(555) 234-5678",
      "mobile": "",
      "fax": "",
      "language": "en",
      "currency_code": "USD",
      "notes": "",
      "p_street1": "123 Fake St.",
      "p_street2": "Unit 555",
      "p_city": "New York",
      "p_state": "New York",
      "p_country": "United States",
      "p_code": 553132,
      "s_street1": "",
      "s_street2": "",
      "s_city": "",
      "s_state": "",
      "s_country": "",
      "s_code": "",
      "vat_name": "",
      "vat_number": "",
      "client_id": 0
    },
    {
      "first_name": "Jane",
      "last_name": "Doe",
      "organization": "ABC Corp",
      "email": "janedoe1@freshbooks.com",
      "username": "janedoe",
      "password": "seCret!7",
      "contacts": {
        "contact": {
          "username": "alex",
          "first_name": "",
          "last_name": "",
          "email": "test@freshbooks.com",
          "phone1": "",
          "phone2": ""
        }
      },
      "work_phone": "(555) 123-4567",
      "home_phone": "(555) 234-5678",
      "mobile": "",
      "fax": "",
      "language": "en",
      "currency_code": "USD",
      "notes": "",
      "p_street1": "123 Fake St.",
      "p_street2": "Unit 555",
      "p_city": "New York",
      "p_state": "New York",
      "p_country": "United States",
      "p_code": 553132,
      "s_street1": "",
      "s_street2": "",
      "s_city": "",
      "s_state": "",
      "s_country": "",
      "s_code": "",
      "vat_name": "",
      "vat_number": "",
      "client_id": 1
    },
    {
      "first_name": "Jane",
      "last_name": "Doe",
      "organization": "ABC Corp",
      "email": "janedoe2@freshbooks.com",
      "username": "janedoe",
      "password": "seCret!7",
      "contacts": {
        "contact": {
          "username": "alex",
          "first_name": "",
          "last_name": "",
          "email": "test@freshbooks.com",
          "phone1": "",
          "phone2": ""
        }
      },
      "work_phone": "(555) 123-4567",
      "home_phone": "(555) 234-5678",
      "mobile": "",
      "fax": "",
      "language": "en",
      "currency_code": "USD",
      "notes": "",
      "p_street1": "123 Fake St.",
      "p_street2": "Unit 555",
      "p_city": "New York",
      "p_state": "New York",
      "p_country": "United States",
      "p_code": 553132,
      "s_street1": "",
      "s_street2": "",
      "s_city": "",
      "s_state": "",
      "s_country": "",
      "s_code": "",
      "vat_name": "",
      "vat_number": "",
      "client_id": 2
    },
    {
      "first_name": "Jane",
      "last_name": "Doe",
      "organization": "ABC Corp",
      "email": "janedoe3@freshbooks.com",
      "username": "janedoe",
      "password": "seCret!7",
      "contacts": {
        "contact": {
          "username": "alex",
          "first_name": "",
          "last_name": "",
          "email": "test@freshbooks.com",
          "phone1": "",
          "phone2": ""
        }
      },
      "work_phone": "(555) 123-4567",
      "home_phone": "(555) 234-5678",
      "mobile": "",
      "fax": "",
      "language": "en",
      "currency_code": "USD",
      "notes": "",
      "p_street1": "123 Fake St.",
      "p_street2": "Unit 555",
      "p_city": "New York",
      "p_state": "New York",
      "p_country": "United States",
      "p_code": 553132,
      "s_street1": "",
      "s_street2": "",
      "s_city": "",
      "s_state": "",
      "s_country": "",
      "s_code": "",
      "vat_name": "",
      "vat_number": "",
      "client_id": 3
    }
  ],
  "invoices": [
    {
      "invoice_id": "00000633766",
      "client_id": 1,
      "contacts": {
        "contact": {
          "contact_id": "0"
        }
      },
      "number": "0000035",
      "amount": "45.6",
      "currency_code": "CAD",
      "language": "en",
      "amount_outstanding": "0",
      "status": "draft",
      "date": "2007-06-23",
      "folder": "active",
      "po_number": [],
      "discount": 0,
      "notes": "Due upon receipt.",
      "terms": "Payment due in 30 days.",
      "url": {
        "_attr_deprecated": "true",
        "#text": "https://2ndsite.freshbooks.com/view/St2gThi6rA2t7RQ"
      },
      "auth_url": {
        "_attr_deprecated": "true",
        "#text": "https://2ndsite.freshbooks.com/invoices/344"
      },
      "links": {
        "client_view": "https://2ndsite.freshbooks.com/view/St2gThi6rA2t7RQ",
        "view": "https://2ndsite.freshbooks.com/invoices/344",
        "edit": "https://2ndsite.freshbooks.com/invoices/344/edit"
      },
      "return_uri": "http://www.example.com/callback",
      "updated": "2009-08-12 09:00:00",
      "recurring_id": 15,
      "organization": "ABC Corp",
      "first_name": "John",
      "last_name": "Doe",
      "p_street1": "123 Fake St.",
      "p_street2": "Unit 555",
      "p_city": "New York",
      "p_state": "New York",
      "p_country": "United States",
      "p_code": 553132,
      "vat_name": [],
      "vat_number": [],
      "staff_id": "1",
      "lines": {
        "line": {
          "line_id": 1,
          "amount": 40,
          "name": "Yard work",
          "description": "Mowed the lawn",
          "unit_cost": 10,
          "quantity": 4,
          "tax1_name": "GST",
          "tax2_name": "PST",
          "tax1_percent": 5,
          "tax2_percent": 8,
          "type": "Item"
        }
      }
    }
  ],
  "payments": [
    {
      "payment_id": 1,
      "client_id": 1,
      "invoice_id": "00000633766",
      "date": "2019-11-30 00: 00: 00",
      "amount": 37,
      "currency_code": "USD",
      "type": "VISA",
      "note": "Portal Payment November",
      "updated": "2019-11-30 04: 00: 00",
      "gateway_transaction": {
        "reference_id": 1,
        "gateway_name": "Auhtorize.Net"
      }
    },
    {
      "payment_id": 2,
      "client_id": 1,
      "invoice_id": 1,
      "date": "2019-11-30 00: 00: 00",
      "amount": 37,
      "currency_code": "USD",
      "type": "VISA",
      "note": "Portal Payment November",
      "updated": "2019-11-30 04: 00: 00",
      "gateway_transaction": {
        "reference_id": 1,
        "gateway_name": "Auhtorize.Net"
      }
    }
  ],
  "seq": {
    "clients": 4,
    "invoices": 1,
    "payments": 2
  }
}